UART/counter.v
module Counter #(parameter OUTPUT_WIDTH = 4)
(   output reg [OUTPUT_WIDTH-1 : 0] value,
    input wire clk,
    input wire enable,
    input wire reset,
    input wire [OUTPUT_WIDTH-1 : 0] load_value,
    input wire [OUTPUT_WIDTH-1 : 0] reset_value
);

    always @(negedge reset) value <= load_value;

    always @(posedge clk) begin
        if(!enable)begin
            if(value + 1 > reset_value) value <= load_value;
            else value <= value + 1;
        end
    end
endmodule

UART/RX.v
module UART_RX(
    input wire clk,
    input wire data_line,
    input wire [15:0] baud_rate_control,
    input wire reset,
    output reg [7:0] read_buffer
);

parameter IDEL_STATE = 3'b00;
parameter START_BIT_STATE = 3'b01;
parameter RECV_STATE = 3'b10;
parameter WAITE_STATE  = 3'b11;
parameter END_BIT_STATE  = 3'b100; 

reg [2:0] previous_state;               // (MEMORY ELEMENT) store previous state of the FSM
reg [2:0] state;                        // (MEMORY ELEMENT) store the current state of the FSM
reg [7:0] buffer;                       // (MEMORY ELEMENT) data buffer

reg [2:0] next_state;                   // (NET) next state evaluated by the FSM and to be stored in state
reg valid_data;                         // (NET) data valid flag used to put the read data from the read buffer to the output
reg half_period_counter_enable;         // (NET) enable half_period_counter
reg inc;                                // (NET) enable bit_counter
reg bit_reset;                          // (NET) reset bit_counter
reg reset_half_period_counter;          // (NET) reset half_period_counter

wire [15:0] half_perid_counter_value;   // value of the half period counter
wire half_period_counter_reset;         // reset of the half period counter
wire [15:0] half_period_counter_reset_value; // used to define the half period counter limit
wire half_period_flag;                 // used to determine that the half period counter overflowd

wire bit_res;                          // reset of the bit counter
wire [3:0] buffer_bit_count;           // value of the bit counter


Counter #(16) half_period_counter (.clk(clk),
                                   .load_value(16'h0000),
                                   .value(half_perid_counter_value),
                                   .enable(half_period_counter_enable),
                                   .reset(half_period_counter_reset),
                                   .reset_value(half_period_counter_reset_value));

Counter #(4) bit_counter           (.clk(!clk),
                                    .load_value(4'b0000),
                                    .value(buffer_bit_count),
                                    .enable(!inc),
                                    .reset(bit_res),
                                    .reset_value(4'b1000));


assign half_period_flag = half_perid_counter_value == ((baud_rate_control >> 1) - 1) ? 1 : 0;
assign half_period_counter_reset_value = (baud_rate_control >> 1) - 1;
assign half_period_counter_reset = reset_half_period_counter & reset;
assign bit_res = bit_reset & reset;

always @(posedge clk)begin
    // DEFAULT VALUES
    previous_state <= previous_state;
    state <= next_state;
    inc = 0;
    bit_reset = 1;
    valid_data = 0;
    // AT HALF THE PERIOD UPDATE THE PREVIOUS STATE
    if(half_period_flag) previous_state <= state;
end

always @(valid_data)begin
    // DEFAULT VALUES
    read_buffer <= read_buffer;
    buffer <= buffer;
    // IF DATA VALID FLAG IS HIGH, MOVE THE DATA FROM THE BUFFER TO THE READ BUFFER AND RESET THEE BUFFER
    if(valid_data)begin
        read_buffer <= buffer;
        buffer <= 8'h00;
    end 
end

always @(buffer_bit_count)begin
    buffer[buffer_bit_count - 1] <= data_line;
end 
// *************************** FSM ***********************************************************************************************
//                                     +-----+            | RELATIONS BETWEEN STATES:
//                                     |RECEV|            |-------------------------
//                                     |STATE|            | 1) IDEAL STATE: when the data line is LOW (possible to be a start bit) 
//                                     +--+--+            |    START BIT STATE: wait for the half period and the data line is HIGH
//                                        ^               |                      not low (false start bit) 
//                                        |3              | 2) wait for the half period and the data line is LOW then the start bit
//   +-----+        +-----+               v               |    condition is met and start to receive bits
//   |IDEAL|   1    |START|    2    +-----+----+          | 3) WAIT STATE: wait for half period then go to receive if the number of 
//   |     +<------>+ BIT +-------->+WAIT STATE|          |                 bit is less than 8
//   |STATE|        |STATE|         +-----+----+          |    RECV STATE: sample the bit and go to wait state
//   +--+--+        +-----+               |               | 4) wait for half period then go to end bit if the number of bit is 
//      ^                                 |4              |    equal to 8 
//      |                                 v               | 5) if data line is HIGH (constrain for end bit) then data in buffer is 
//      |                              +--+--+            |    valid
//      |               5              | END |            |-----------------------------------------------------------------------
//      +------------------------------+ BIT |            |STATES
//                                     |STATE|            |------
//                                     +-----+            |1) IDEAL STATE: no start bit occured
//                                                        |2) START BIT STATE: data line is LOW and it might be a start bit
//                                                        |3) WAIT STATE: wait for half of the baud rate period
//                                                        |4) RECV BIT STATE: receive bits from the data line in the buffer
//                                                        |5) END BIT STATE: check for the ending bit
// ********************************************************************************************************************************

always @(data_line or half_period_flag)begin
    // DEFAULT VALUES
    half_period_counter_enable = half_period_counter_enable;
    next_state = next_state;
    inc = inc;
    bit_reset = bit_reset;
    valid_data = valid_data;
    // RX FSM
    casex(state)
        IDEL_STATE: begin
            if(!data_line)begin 
                half_period_counter_enable = 0;
                next_state = START_BIT_STATE;
            end 
        end
        START_BIT_STATE: begin
            if(half_period_flag) begin
                if(!data_line)begin
                    next_state = WAITE_STATE;
                end else begin
                    next_state = IDEL_STATE;
                end 
            end 
        end
        WAITE_STATE: begin
            if(half_period_flag) begin
                casex(previous_state)
                    START_BIT_STATE: next_state = RECV_STATE; 
                    RECV_STATE: begin
                        if(buffer_bit_count == 8)begin
                            next_state = END_BIT_STATE;
                            inc = 0;
                            bit_reset = 0;
                        end else next_state = RECV_STATE;
                    end
                endcase
            end
        end
        RECV_STATE: begin
            if(half_period_flag) begin
                next_state = WAITE_STATE;
                inc = 1;
            end
        end
        END_BIT_STATE: begin
            if(half_period_flag) begin
                next_state = IDEL_STATE;
                if(data_line) valid_data = 1;
                else valid_data = 0;
            end
        end
        default: begin
            next_state = IDEL_STATE;
            inc = 0;
            bit_reset = 1;
            half_period_counter_enable = 1;
            valid_data = 0;
        end 
    endcase
end

always @(negedge reset)begin
    // Reset all MEMORY ELEMENTS
    previous_state <= IDEL_STATE;
    state <= IDEL_STATE;
    buffer <= 8'h00;
    read_buffer <= 8'h00;
    // Reset Combinational Circuit Nets
    reset_half_period_counter = 1'b1;
    inc = 0;
    bit_reset = 1;
    next_state = IDEL_STATE;
    half_period_counter_enable = 1'b1;
    valid_data = 1'b0;
end

endmodule

UART/TB_RX.v
`include "RX.v"

module UART_TB();

reg clk = 1;
reg data_line = 1;
reg [15:0] uart_baud_control = 8;
reg reset = 1;
wire [7:0] read_data;

UART_RX rx(clk, data_line, uart_baud_control, reset, read_data);

initial begin
    $dumpfile("rx.vcd");
    $dumpvars(0,rx);
    // RESETTING
    reset = 1;
    data_line = 1;
    #10
    reset = 0;
    #5
    reset = 1;
    #15
    // ***************************** FRAME 1 **************************************************
    // START BIT
    data_line = 0; #80
    // DATA
    data_line = 1; #80
    data_line = 0; #80
    data_line = 1; #80
    data_line = 0; #80
    data_line = 1; #80
    data_line = 0; #80
    data_line = 1; #80
    data_line = 0; #80
    // END BIT
    data_line = 1; #80
    // ****************************************************************************************
    // ***************************** FRAME 2 **************************************************
    // START BIT
    data_line = 0; #80
    // DATA
    data_line = 0; #80
    data_line = 0; #80
    data_line = 1; #80
    data_line = 1; #80
    data_line = 0; #80
    data_line = 0; #80
    data_line = 1; #80
    data_line = 1; #80
    // END BIT
    data_line = 1; #80
    // ****************************************************************************************
    data_line = 1; #120
    $finish();
end

always begin
    #5 clk = ~clk;
end

endmodule

UART/rx.vcd
$date
	Sun Sep  6 15:02:41 2020
$end
$version
	Icarus Verilog
$end
$timescale
	1s
$end
$scope module UART_TB $end
$scope module rx $end
$var wire 16 ! baud_rate_control [15:0] $end
$var wire 1 " bit_res $end
$var wire 1 # clk $end
$var wire 1 $ data_line $end
$var wire 1 % half_period_counter_reset $end
$var wire 1 & reset $end
$var wire 1 ' half_period_flag $end
$var wire 16 ( half_period_counter_reset_value [15:0] $end
$var wire 16 ) half_perid_counter_value [15:0] $end
$var wire 4 * buffer_bit_count [3:0] $end
$var reg 1 + bit_reset $end
$var reg 8 , buffer [7:0] $end
$var reg 1 - half_period_counter_enable $end
$var reg 1 . inc $end
$var reg 3 / next_state [2:0] $end
$var reg 3 0 previous_state [2:0] $end
$var reg 8 1 read_buffer [7:0] $end
$var reg 1 2 reset_half_period_counter $end
$var reg 3 3 state [2:0] $end
$var reg 1 4 valid_data $end
$scope module bit_counter $end
$var wire 1 5 clk $end
$var wire 1 6 enable $end
$var wire 4 7 load_value [3:0] $end
$var wire 1 " reset $end
$var wire 4 8 reset_value [3:0] $end
$var reg 4 9 value [3:0] $end
$upscope $end
$scope module half_period_counter $end
$var wire 1 # clk $end
$var wire 1 - enable $end
$var wire 16 : load_value [15:0] $end
$var wire 1 % reset $end
$var wire 16 ; reset_value [15:0] $end
$var reg 16 < value [15:0] $end
$upscope $end
$upscope $end
$upscope $end
$enddefinitions $end
#0
$dumpvars
bx <
b11 ;
b0 :
bx 9
b1000 8
b0 7
16
05
04
bx 3
x2
bx 1
bx 0
bx /
0.
x-
bx ,
1+
bx *
bx )
b11 (
x'
1&
x%
1$
1#
1"
b1000 !
$end
#5
15
0#
#10
0'
b0 )
b0 <
b0 *
b0 9
b0 1
b0 ,
b0 3
bx 0
0%
0"
1-
b0 /
12
05
1#
0&
#15
1%
1"
15
0#
1&
#20
05
1#
#25
15
0#
#30
b1 3
b1 )
b1 <
b1 /
0-
05
1#
0$
#35
15
0#
#40
b10 )
b10 <
05
1#
#45
15
0#
#50
b11 /
1'
b11 )
b11 <
05
1#
#55
15
0#
#60
0'
b0 )
b0 <
b1 0
b11 3
05
1#
#65
15
0#
#70
b1 )
b1 <
05
1#
#75
15
0#
#80
b10 )
b10 <
05
1#
#85
15
0#
#90
b10 /
1'
b11 )
b11 <
05
1#
#95
15
0#
#100
0'
b0 )
b0 <
b11 0
b10 3
05
1#
#105
15
0#
#110
b1 )
b1 <
05
1#
1$
#115
15
0#
#120
b10 )
b10 <
05
1#
#125
15
0#
#130
06
1.
b11 /
1'
b11 )
b11 <
05
1#
#135
b1 ,
b1 *
b1 9
15
0#
#140
0'
b0 )
b0 <
b10 0
b11 3
16
0.
05
1#
#145
15
0#
#150
b1 )
b1 <
05
1#
#155
15
0#
#160
b10 )
b10 <
05
1#
#165
15
0#
#170
b10 /
1'
b11 )
b11 <
05
1#
#175
15
0#
#180
0'
b0 )
b0 <
b11 0
b10 3
05
1#
#185
15
0#
#190
b1 )
b1 <
05
1#
0$
#195
15
0#
#200
b10 )
b10 <
05
1#
#205
15
0#
#210
06
1.
b11 /
1'
b11 )
b11 <
05
1#
#215
b10 *
b10 9
15
0#
#220
0'
b0 )
b0 <
b10 0
b11 3
16
0.
05
1#
#225
15
0#
#230
b1 )
b1 <
05
1#
#235
15
0#
#240
b10 )
b10 <
05
1#
#245
15
0#
#250
b10 /
1'
b11 )
b11 <
05
1#
#255
15
0#
#260
0'
b0 )
b0 <
b11 0
b10 3
05
1#
#265
15
0#
#270
b1 )
b1 <
05
1#
1$
#275
15
0#
#280
b10 )
b10 <
05
1#
#285
15
0#
#290
06
1.
b11 /
1'
b11 )
b11 <
05
1#
#295
b101 ,
b11 *
b11 9
15
0#
#300
0'
b0 )
b0 <
b10 0
b11 3
16
0.
05
1#
#305
15
0#
#310
b1 )
b1 <
05
1#
#315
15
0#
#320
b10 )
b10 <
05
1#
#325
15
0#
#330
b10 /
1'
b11 )
b11 <
05
1#
#335
15
0#
#340
0'
b0 )
b0 <
b11 0
b10 3
05
1#
#345
15
0#
#350
b1 )
b1 <
05
1#
0$
#355
15
0#
#360
b10 )
b10 <
05
1#
#365
15
0#
#370
06
1.
b11 /
1'
b11 )
b11 <
05
1#
#375
b100 *
b100 9
15
0#
#380
0'
b0 )
b0 <
b10 0
b11 3
16
0.
05
1#
#385
15
0#
#390
b1 )
b1 <
05
1#
#395
15
0#
#400
b10 )
b10 <
05
1#
#405
15
0#
#410
b10 /
1'
b11 )
b11 <
05
1#
#415
15
0#
#420
0'
b0 )
b0 <
b11 0
b10 3
05
1#
#425
15
0#
#430
b1 )
b1 <
05
1#
1$
#435
15
0#
#440
b10 )
b10 <
05
1#
#445
15
0#
#450
06
1.
b11 /
1'
b11 )
b11 <
05
1#
#455
b10101 ,
b101 *
b101 9
15
0#
#460
0'
b0 )
b0 <
b10 0
b11 3
16
0.
05
1#
#465
15
0#
#470
b1 )
b1 <
05
1#
#475
15
0#
#480
b10 )
b10 <
05
1#
#485
15
0#
#490
b10 /
1'
b11 )
b11 <
05
1#
#495
15
0#
#500
0'
b0 )
b0 <
b11 0
b10 3
05
1#
#505
15
0#
#510
b1 )
b1 <
05
1#
0$
#515
15
0#
#520
b10 )
b10 <
05
1#
#525
15
0#
#530
06
1.
b11 /
1'
b11 )
b11 <
05
1#
#535
b110 *
b110 9
15
0#
#540
0'
b0 )
b0 <
b10 0
b11 3
16
0.
05
1#
#545
15
0#
#550
b1 )
b1 <
05
1#
#555
15
0#
#560
b10 )
b10 <
05
1#
#565
15
0#
#570
b10 /
1'
b11 )
b11 <
05
1#
#575
15
0#
#580
0'
b0 )
b0 <
b11 0
b10 3
05
1#
#585
15
0#
#590
b1 )
b1 <
05
1#
1$
#595
15
0#
#600
b10 )
b10 <
05
1#
#605
15
0#
#610
06
1.
b11 /
1'
b11 )
b11 <
05
1#
#615
b1010101 ,
b111 *
b111 9
15
0#
#620
0'
b0 )
b0 <
b10 0
b11 3
16
0.
05
1#
#625
15
0#
#630
b1 )
b1 <
05
1#
#635
15
0#
#640
b10 )
b10 <
05
1#
#645
15
0#
#650
b10 /
1'
b11 )
b11 <
05
1#
#655
15
0#
#660
0'
b0 )
b0 <
b11 0
b10 3
05
1#
#665
15
0#
#670
b1 )
b1 <
05
1#
0$
#675
15
0#
#680
b10 )
b10 <
05
1#
#685
15
0#
#690
06
1.
b11 /
1'
b11 )
b11 <
05
1#
#695
b1000 *
b1000 9
15
0#
#700
0'
b0 )
b0 <
b10 0
b11 3
16
0.
05
1#
#705
15
0#
#710
b1 )
b1 <
05
1#
#715
15
0#
#720
b10 )
b10 <
05
1#
#725
15
0#
#730
b0 *
b0 9
0"
0+
b100 /
1'
b11 )
b11 <
05
1#
#735
15
0#
#740
0'
b0 )
b0 <
b11 0
b100 3
1"
1+
05
1#
#745
15
0#
#750
b1 )
b1 <
05
1#
1$
#755
15
0#
#760
b10 )
b10 <
05
1#
#765
15
0#
#770
b0 ,
b1010101 1
14
b0 /
1'
b11 )
b11 <
05
1#
#775
15
0#
#780
0'
b0 )
b0 <
b100 0
b0 3
04
05
1#
#785
15
0#
#790
b1 )
b1 <
05
1#
#795
15
0#
#800
b10 )
b10 <
05
1#
#805
15
0#
#810
1'
b11 )
b11 <
05
1#
#815
15
0#
#820
0'
b0 )
b0 <
b0 0
05
1#
#825
15
0#
#830
b1 3
b1 )
b1 <
b1 /
05
1#
0$
#835
15
0#
#840
b10 )
b10 <
05
1#
#845
15
0#
#850
b11 /
1'
b11 )
b11 <
05
1#
#855
15
0#
#860
0'
b0 )
b0 <
b1 0
b11 3
05
1#
#865
15
0#
#870
b1 )
b1 <
05
1#
#875
15
0#
#880
b10 )
b10 <
05
1#
#885
15
0#
#890
b10 /
1'
b11 )
b11 <
05
1#
#895
15
0#
#900
0'
b0 )
b0 <
b11 0
b10 3
05
1#
#905
15
0#
#910
b1 )
b1 <
05
1#
#915
15
0#
#920
b10 )
b10 <
05
1#
#925
15
0#
#930
06
1.
b11 /
1'
b11 )
b11 <
05
1#
#935
b1 *
b1 9
15
0#
#940
0'
b0 )
b0 <
b10 0
b11 3
16
0.
05
1#
#945
15
0#
#950
b1 )
b1 <
05
1#
#955
15
0#
#960
b10 )
b10 <
05
1#
#965
15
0#
#970
b10 /
1'
b11 )
b11 <
05
1#
#975
15
0#
#980
0'
b0 )
b0 <
b11 0
b10 3
05
1#
#985
15
0#
#990
b1 )
b1 <
05
1#
#995
15
0#
#1000
b10 )
b10 <
05
1#
#1005
15
0#
#1010
06
1.
b11 /
1'
b11 )
b11 <
05
1#
#1015
b10 *
b10 9
15
0#
#1020
0'
b0 )
b0 <
b10 0
b11 3
16
0.
05
1#
#1025
15
0#
#1030
b1 )
b1 <
05
1#
#1035
15
0#
#1040
b10 )
b10 <
05
1#
#1045
15
0#
#1050
b10 /
1'
b11 )
b11 <
05
1#
#1055
15
0#
#1060
0'
b0 )
b0 <
b11 0
b10 3
05
1#
#1065
15
0#
#1070
b1 )
b1 <
05
1#
1$
#1075
15
0#
#1080
b10 )
b10 <
05
1#
#1085
15
0#
#1090
06
1.
b11 /
1'
b11 )
b11 <
05
1#
#1095
b100 ,
b11 *
b11 9
15
0#
#1100
0'
b0 )
b0 <
b10 0
b11 3
16
0.
05
1#
#1105
15
0#
#1110
b1 )
b1 <
05
1#
#1115
15
0#
#1120
b10 )
b10 <
05
1#
#1125
15
0#
#1130
b10 /
1'
b11 )
b11 <
05
1#
#1135
15
0#
#1140
0'
b0 )
b0 <
b11 0
b10 3
05
1#
#1145
15
0#
#1150
b1 )
b1 <
05
1#
#1155
15
0#
#1160
b10 )
b10 <
05
1#
#1165
15
0#
#1170
06
1.
b11 /
1'
b11 )
b11 <
05
1#
#1175
b1100 ,
b100 *
b100 9
15
0#
#1180
0'
b0 )
b0 <
b10 0
b11 3
16
0.
05
1#
#1185
15
0#
#1190
b1 )
b1 <
05
1#
#1195
15
0#
#1200
b10 )
b10 <
05
1#
#1205
15
0#
#1210
b10 /
1'
b11 )
b11 <
05
1#
#1215
15
0#
#1220
0'
b0 )
b0 <
b11 0
b10 3
05
1#
#1225
15
0#
#1230
b1 )
b1 <
05
1#
0$
#1235
15
0#
#1240
b10 )
b10 <
05
1#
#1245
15
0#
#1250
06
1.
b11 /
1'
b11 )
b11 <
05
1#
#1255
b101 *
b101 9
15
0#
#1260
0'
b0 )
b0 <
b10 0
b11 3
16
0.
05
1#
#1265
15
0#
#1270
b1 )
b1 <
05
1#
#1275
15
0#
#1280
b10 )
b10 <
05
1#
#1285
15
0#
#1290
b10 /
1'
b11 )
b11 <
05
1#
#1295
15
0#
#1300
0'
b0 )
b0 <
b11 0
b10 3
05
1#
#1305
15
0#
#1310
b1 )
b1 <
05
1#
#1315
15
0#
#1320
b10 )
b10 <
05
1#
#1325
15
0#
#1330
06
1.
b11 /
1'
b11 )
b11 <
05
1#
#1335
b110 *
b110 9
15
0#
#1340
0'
b0 )
b0 <
b10 0
b11 3
16
0.
05
1#
#1345
15
0#
#1350
b1 )
b1 <
05
1#
#1355
15
0#
#1360
b10 )
b10 <
05
1#
#1365
15
0#
#1370
b10 /
1'
b11 )
b11 <
05
1#
#1375
15
0#
#1380
0'
b0 )
b0 <
b11 0
b10 3
05
1#
#1385
15
0#
#1390
b1 )
b1 <
05
1#
1$
#1395
15
0#
#1400
b10 )
b10 <
05
1#
#1405
15
0#
#1410
06
1.
b11 /
1'
b11 )
b11 <
05
1#
#1415
b1001100 ,
b111 *
b111 9
15
0#
#1420
0'
b0 )
b0 <
b10 0
b11 3
16
0.
05
1#
#1425
15
0#
#1430
b1 )
b1 <
05
1#
#1435
15
0#
#1440
b10 )
b10 <
05
1#
#1445
15
0#
#1450
b10 /
1'
b11 )
b11 <
05
1#
#1455
15
0#
#1460
0'
b0 )
b0 <
b11 0
b10 3
05
1#
#1465
15
0#
#1470
b1 )
b1 <
05
1#
#1475
15
0#
#1480
b10 )
b10 <
05
1#
#1485
15
0#
#1490
06
1.
b11 /
1'
b11 )
b11 <
05
1#
#1495
b11001100 ,
b1000 *
b1000 9
15
0#
#1500
0'
b0 )
b0 <
b10 0
b11 3
16
0.
05
1#
#1505
15
0#
#1510
b1 )
b1 <
05
1#
#1515
15
0#
#1520
b10 )
b10 <
05
1#
#1525
15
0#
#1530
b0 *
b0 9
0"
0+
b100 /
1'
b11 )
b11 <
05
1#
#1535
15
0#
#1540
0'
b0 )
b0 <
b11 0
b100 3
1"
1+
05
1#
#1545
15
0#
#1550
b1 )
b1 <
05
1#
#1555
15
0#
#1560
b10 )
b10 <
05
1#
#1565
15
0#
#1570
b0 ,
b11001100 1
14
b0 /
1'
b11 )
b11 <
05
1#
#1575
15
0#
#1580
0'
b0 )
b0 <
b100 0
b0 3
04
05
1#
#1585
15
0#
#1590
b1 )
b1 <
05
1#
#1595
15
0#
#1600
b10 )
b10 <
05
1#
#1605
15
0#
#1610
1'
b11 )
b11 <
05
1#
#1615
15
0#
#1620
0'
b0 )
b0 <
b0 0
05
1#
#1625
15
0#
#1630
b1 )
b1 <
05
1#
#1635
15
0#
#1640
b10 )
b10 <
05
1#
#1645
15
0#
#1650
1'
b11 )
b11 <
05
1#
#1655
15
0#
#1660
0'
b0 )
b0 <
05
1#
#1665
15
0#
#1670
b1 )
b1 <
05
1#
#1675
15
0#
#1680
b10 )
b10 <
05
1#
#1685
15
0#
#1690
1'
b11 )
b11 <
05
1#
#1695
15
0#
#1700
0'
b0 )
b0 <
05
1#
#1705
15
0#
#1710
b1 )
b1 <
05
1#
#1715
15
0#
#1720
b10 )
b10 <
05
1#
#1725
15
0#
#1730
1'
b11 )
b11 <
05
1#
#1735
15
0#
#1740
0'
b0 )
b0 <
05
1#
#1745
15
0#
#1750
b1 )
b1 <
05
1#
