UART/counter.v
module Counter #(parameter OUTPUT_WIDTH = 4)
(   output reg [OUTPUT_WIDTH-1 : 0] value,
    input wire clk,
    input wire enable,
    input wire reset,
    input wire [OUTPUT_WIDTH-1 : 0] load_value,
    input wire [OUTPUT_WIDTH-1 : 0] reset_value
);

    always @(negedge reset) value <= load_value;

    always @(posedge clk) begin
        if(!enable)begin
            if(value + 1 > reset_value) value <= load_value;
            else value <= value + 1;
        end
    end
endmodule

UART/RX.v
module UART_RX(
    input wire clk,
    input wire data_line,
    input wire [15:0] baud_rate_control,
    input wire reset,
    output reg [7:0] read_buffer
);

parameter IDEL_STATE = 3'b00;
parameter START_BIT_STATE = 3'b01;
parameter RECV_STATE = 3'b10;
parameter WAITE_STATE  = 3'b11;
parameter END_BIT_STATE  = 3'b100; 

reg [2:0] previous_state;               // (MEMORY ELEMENT) store previous state of the FSM
reg [2:0] state;                        // (MEMORY ELEMENT) store the current state of the FSM
reg [7:0] buffer;                       // (MEMORY ELEMENT) data buffer

reg [2:0] next_state;                   // (NET) next state evaluated by the FSM and to be stored in state
reg valid_data;                         // (NET) data valid flag used to put the read data from the read buffer to the output
reg half_period_counter_enable;         // (NET) enable half_period_counter
reg inc;                                // (NET) enable bit_counter
reg bit_reset;                          // (NET) reset bit_counter
reg reset_half_period_counter;          // (NET) reset half_period_counter

wire [15:0] half_perid_counter_value;   // value of the half period counter
wire half_period_counter_reset;         // reset of the half period counter
wire [15:0] half_period_counter_reset_value; // used to define the half period counter limit
wire half_period_flag;                 // used to determine that the half period counter overflowd

wire bit_res;                          // reset of the bit counter
wire [3:0] buffer_bit_count;           // value of the bit counter


Counter #(16) half_period_counter (.clk(clk),
                                   .load_value(16'h0000),
                                   .value(half_perid_counter_value),
                                   .enable(half_period_counter_enable),
                                   .reset(half_period_counter_reset),
                                   .reset_value(half_period_counter_reset_value));

Counter #(4) bit_counter           (.clk(!clk),
                                    .load_value(4'b0000),
                                    .value(buffer_bit_count),
                                    .enable(!inc),
                                    .reset(bit_res),
                                    .reset_value(4'b1000));


assign half_period_flag = half_perid_counter_value == ((baud_rate_control >> 1) - 1) ? 1 : 0;
assign half_period_counter_reset_value = (baud_rate_control >> 1) - 1;
assign half_period_counter_reset = reset_half_period_counter & reset;
assign bit_res = bit_reset & reset;

always @(posedge clk)begin
    // DEFAULT VALUES
    previous_state <= previous_state;
    state <= next_state;
    inc = 0;
    bit_reset = 1;
    valid_data = 0;
    // AT HALF THE PERIOD UPDATE THE PREVIOUS STATE
    if(half_period_flag) previous_state <= state;
end

always @(valid_data)begin
    // DEFAULT VALUES
    read_buffer <= read_buffer;
    buffer <= buffer;
    // IF DATA VALID FLAG IS HIGH, MOVE THE DATA FROM THE BUFFER TO THE READ BUFFER AND RESET THEE BUFFER
    if(valid_data)begin
        read_buffer <= buffer;
        buffer <= 8'h00;
    end 
end

always @(buffer_bit_count)begin
    buffer[buffer_bit_count - 1] <= data_line;
end 
// *************************** FSM ***********************************************************************************************
//                                     +-----+            | RELATIONS BETWEEN STATES:
//                                     |RECEV|            |-------------------------
//                                     |STATE|            | 1) IDEAL STATE: when the data line is LOW (possible to be a start bit) 
//                                     +--+--+            |    START BIT STATE: wait for the half period and the data line is HIGH
//                                        ^               |                      not low (false start bit) 
//                                        |3              | 2) wait for the half period and the data line is LOW then the start bit
//   +-----+        +-----+               v               |    condition is met and start to receive bits
//   |IDEAL|   1    |START|    2    +-----+----+          | 3) WAIT STATE: wait for half period then go to receive if the number of 
//   |     +<------>+ BIT +-------->+WAIT STATE|          |                 bit is less than 8
//   |STATE|        |STATE|         +-----+----+          |    RECV STATE: sample the bit and go to wait state
//   +--+--+        +-----+               |               | 4) wait for half period then go to end bit if the number of bit is 
//      ^                                 |4              |    equal to 8 
//      |                                 v               | 5) if data line is HIGH (constrain for end bit) then data in buffer is 
//      |                              +--+--+            |    valid
//      |               5              | END |            |-----------------------------------------------------------------------
//      +------------------------------+ BIT |            |STATES
//                                     |STATE|            |------
//                                     +-----+            |1) IDEAL STATE: no start bit occured
//                                                        |2) START BIT STATE: data line is LOW and it might be a start bit
//                                                        |3) WAIT STATE: wait for half of the baud rate period
//                                                        |4) RECV BIT STATE: receive bits from the data line in the buffer
//                                                        |5) END BIT STATE: check for the ending bit
// ********************************************************************************************************************************

always @(data_line or half_period_flag)begin
    // DEFAULT VALUES
    half_period_counter_enable = half_period_counter_enable;
    next_state = next_state;
    inc = inc;
    bit_reset = bit_reset;
    valid_data = valid_data;
    // RX FSM
    casex(state)
        IDEL_STATE: begin
            if(!data_line)begin 
                half_period_counter_enable = 0;
                next_state = START_BIT_STATE;
            end 
        end
        START_BIT_STATE: begin
            if(half_period_flag) begin
                if(!data_line)begin
                    next_state = WAITE_STATE;
                end else begin
                    next_state = IDEL_STATE;
                end 
            end 
        end
        WAITE_STATE: begin
            if(half_period_flag) begin
                casex(previous_state)
                    START_BIT_STATE: next_state = RECV_STATE; 
                    RECV_STATE: begin
                        if(buffer_bit_count == 8)begin
                            next_state = END_BIT_STATE;
                            inc = 0;
                            bit_reset = 0;
                        end else next_state = RECV_STATE;
                    end
                endcase
            end
        end
        RECV_STATE: begin
            if(half_period_flag) begin
                next_state = WAITE_STATE;
                inc = 1;
            end
        end
        END_BIT_STATE: begin
            if(half_period_flag) begin
                next_state = IDEL_STATE;
                if(data_line) valid_data = 1;
                else valid_data = 0;
            end
        end
        default: begin
            next_state = IDEL_STATE;
            inc = 0;
            bit_reset = 1;
            half_period_counter_enable = 1;
            valid_data = 0;
        end 
    endcase
end

always @(negedge reset)begin
    // Reset all MEMORY ELEMENTS
    previous_state <= IDEL_STATE;
    state <= IDEL_STATE;
    buffer <= 8'h00;
    read_buffer <= 8'h00;
    // Reset Combinational Circuit Nets
    reset_half_period_counter = 1'b1;
    inc = 0;
    bit_reset = 1;
    next_state = IDEL_STATE;
    half_period_counter_enable = 1'b1;
    valid_data = 1'b0;
end

endmodule

UART/TX.v
module UART_TX(
    input wire clk,
    input wire  [7:0] write_buffer,
    input wire [15:0] baud_rate_control,
    input wire send,
    input wire reset,
    output reg data_line,
    output reg busy
);

parameter BUSY = 1'b1;
parameter IDEAL = 1'b0;

reg [9:0] buffer;
reg state;

reg next_state;
reg period_counter_enable;
reg send_bit_counter_inc;
reg send_bit_counter_reset;

wire [15:0] perid_counter_value;
wire [3:0] send_bit_counter_value;

wire full_period_flag = perid_counter_value == 0 ? 1 : 0;

Counter #(16) period_counter (.clk(clk),
                              .load_value(16'h0000),
                              .value(perid_counter_value),
                              .enable(period_counter_enable),
                              .reset(reset),
                              .reset_value(baud_rate_control - 1));

Counter #(4) send_bit_counter      (.clk(!clk),
                                    .load_value(4'b0000),
                                    .value(send_bit_counter_value),
                                    .enable(!send_bit_counter_inc),
                                    .reset(send_bit_counter_reset),
                                    .reset_value(4'd10));

always @(posedge clk)begin
    state <= next_state;
    send_bit_counter_inc = 0;
    send_bit_counter_reset = 1;
end

always @(posedge send or state or posedge full_period_flag)begin
    next_state = next_state;
    send_bit_counter_reset = send_bit_counter_reset;
    send_bit_counter_inc = send_bit_counter_inc;
    period_counter_enable = period_counter_enable;
    busy = busy;
    casex(state)
        IDEAL: begin
            data_line <= 1;
            busy = 0;
            if(send) begin
                buffer <= {1'b1, write_buffer, 1'b0};
                next_state = BUSY;
                send_bit_counter_reset = 0;
            end
        end
        BUSY: begin
            period_counter_enable = 0;
            send_bit_counter_inc = 1;
            busy = 1;
            data_line <= buffer[send_bit_counter_value];
            if(send_bit_counter_value == 10)begin 
                next_state = IDEAL;
                data_line <= 1;
            end
        end
        default: data_line <= 1;
    endcase
end

always @(negedge reset)begin
    state <= IDEAL;
    buffer <= 10'h000;
    next_state = IDEAL;
    period_counter_enable = 1;
    data_line = 1;
    // period_counter_reset = 1;
    send_bit_counter_inc = 0;
    send_bit_counter_reset = 1;

end

endmodule

UART/TB_UART.v
`include "counter.v"
`include "TX.v"
`include "RX.v"

module UART_TB();

reg clk = 1;
reg [7:0] write_buffer;
reg [15:0] uart_baud_control = 8;
reg send = 0;
reg reset = 1;
wire [7:0] read_data;
wire data_line;
wire busy;

UART_TX tx(clk, write_buffer, uart_baud_control, send, reset, data_line, busy);
UART_RX rx(clk, data_line, uart_baud_control, reset, read_data);


initial begin
    $dumpfile("uart.vcd");
    $dumpvars(0,tx);
    $dumpvars(0,rx);
    // RESETTING
    reset = 1;
    #10
    reset = 0;
    #10
    reset = 1;
    // Write Frame
    write_buffer = 8'b10101010;
    send = 1;
    #10
    send = 0;
    #790
    // Write Frame
    write_buffer = 8'b11110000;
    send = 1;
    #10
    send = 0;
    #790
    // Write Frame
    write_buffer = 8'b00001111;
    send = 1;
    #10
    send = 0;
    #790
    // Write Frame
    write_buffer = 8'b11001100;
    send = 1;
    #10
    send = 0;
    #790
    // Write Frame
    write_buffer = 8'b11101110;
    send = 1;
    #10
    send = 0;
    #790
    #800
    $finish();
end

always begin
    #5 clk = ~clk;
end

endmodule

UART/uart.vcd
$date
	Sun Sep  6 15:02:57 2020
$end
$version
	Icarus Verilog
$end
$timescale
	1s
$end
$scope module UART_TB $end
$scope module tx $end
$var wire 16 ! baud_rate_control [15:0] $end
$var wire 1 " clk $end
$var wire 1 # reset $end
$var wire 1 $ send $end
$var wire 8 % write_buffer [7:0] $end
$var wire 4 & send_bit_counter_value [3:0] $end
$var wire 16 ' perid_counter_value [15:0] $end
$var wire 1 ( full_period_flag $end
$var reg 10 ) buffer [9:0] $end
$var reg 1 * busy $end
$var reg 1 + data_line $end
$var reg 1 , next_state $end
$var reg 1 - period_counter_enable $end
$var reg 1 . send_bit_counter_inc $end
$var reg 1 / send_bit_counter_reset $end
$var reg 1 0 state $end
$scope module period_counter $end
$var wire 1 " clk $end
$var wire 1 - enable $end
$var wire 16 1 load_value [15:0] $end
$var wire 1 # reset $end
$var wire 16 2 reset_value [15:0] $end
$var reg 16 3 value [15:0] $end
$upscope $end
$scope module send_bit_counter $end
$var wire 1 4 clk $end
$var wire 1 5 enable $end
$var wire 4 6 load_value [3:0] $end
$var wire 1 / reset $end
$var wire 4 7 reset_value [3:0] $end
$var reg 4 8 value [3:0] $end
$upscope $end
$upscope $end
$upscope $end
$scope module UART_TB $end
$scope module rx $end
$var wire 16 9 baud_rate_control [15:0] $end
$var wire 1 : bit_res $end
$var wire 1 " clk $end
$var wire 1 ; half_period_counter_reset $end
$var wire 1 # reset $end
$var wire 1 < half_period_flag $end
$var wire 16 = half_period_counter_reset_value [15:0] $end
$var wire 16 > half_perid_counter_value [15:0] $end
$var wire 1 + data_line $end
$var wire 4 ? buffer_bit_count [3:0] $end
$var reg 1 @ bit_reset $end
$var reg 8 A buffer [7:0] $end
$var reg 1 B half_period_counter_enable $end
$var reg 1 C inc $end
$var reg 3 D next_state [2:0] $end
$var reg 3 E previous_state [2:0] $end
$var reg 8 F read_buffer [7:0] $end
$var reg 1 G reset_half_period_counter $end
$var reg 3 H state [2:0] $end
$var reg 1 I valid_data $end
$scope module bit_counter $end
$var wire 1 J clk $end
$var wire 1 K enable $end
$var wire 4 L load_value [3:0] $end
$var wire 1 : reset $end
$var wire 4 M reset_value [3:0] $end
$var reg 4 N value [3:0] $end
$upscope $end
$scope module half_period_counter $end
$var wire 1 " clk $end
$var wire 1 B enable $end
$var wire 16 O load_value [15:0] $end
$var wire 1 ; reset $end
$var wire 16 P reset_value [15:0] $end
$var reg 16 Q value [15:0] $end
$upscope $end
$upscope $end
$upscope $end
$enddefinitions $end
#0
$dumpvars
bx Q
b11 P
b0 O
bx N
b1000 M
b0 L
1K
0J
0I
bx H
xG
bx F
bx E
bx D
0C
xB
bx A
1@
bx ?
bx >
b11 =
x<
x;
1:
b1000 9
bx 8
b1010 7
b0 6
15
04
bx 3
b111 2
b0 1
x0
1/
0.
x-
x,
x+
x*
bx )
x(
bx '
bx &
bx %
0$
1#
1"
b1000 !
$end
#5
1J
14
0"
#10
0<
1(
0*
b0 >
b0 Q
b0 ?
b0 N
b0 '
b0 3
b0 )
00
b0 F
b0 A
b0 H
bx E
0;
0:
1+
1-
0,
1B
b0 D
1G
0J
04
1"
0#
#15
1J
14
0"
#20
b1 D
0B
0+
1*
05
1.
0-
b0 &
b0 8
10
b1101010100 )
1/
1,
1;
1:
0J
04
1"
1$
b10101010 %
1#
#25
b1 &
b1 8
1J
14
0"
#30
0(
b1 H
b1 >
b1 Q
b1 '
b1 3
15
0.
0J
04
1"
0$
#35
1J
14
0"
#40
b10 '
b10 3
b10 >
b10 Q
0J
04
1"
#45
1J
14
0"
#50
b11 D
1<
b11 >
b11 Q
b11 '
b11 3
0J
04
1"
#55
1J
14
0"
#60
0<
b100 '
b100 3
b0 >
b0 Q
b1 E
b11 H
0J
04
1"
#65
1J
14
0"
#70
b1 >
b1 Q
b101 '
b101 3
0J
04
1"
#75
1J
14
0"
#80
b110 '
b110 3
b10 >
b10 Q
0J
04
1"
#85
1J
14
0"
#90
b10 D
1<
b11 >
b11 Q
b111 '
b111 3
0J
04
1"
#95
1J
14
0"
#100
05
1.
1(
0<
b0 '
b0 3
b0 >
b0 Q
b11 E
b10 H
0J
04
1"
#105
b10 &
b10 8
1J
14
0"
#110
0(
b1 >
b1 Q
b1 '
b1 3
15
0.
0J
04
1"
#115
1J
14
0"
#120
b10 '
b10 3
b10 >
b10 Q
0J
04
1"
#125
1J
14
0"
#130
0K
1C
b11 D
1<
b11 >
b11 Q
b11 '
b11 3
0J
04
1"
#135
b1 ?
b1 N
1J
14
0"
#140
0<
b100 '
b100 3
b0 >
b0 Q
b10 E
b11 H
1K
0C
0J
04
1"
#145
1J
14
0"
#150
b1 >
b1 Q
b101 '
b101 3
0J
04
1"
#155
1J
14
0"
#160
b110 '
b110 3
b10 >
b10 Q
0J
04
1"
#165
1J
14
0"
#170
b10 D
1<
b11 >
b11 Q
b111 '
b111 3
0J
04
1"
#175
1J
14
0"
#180
1+
05
1.
1(
0<
b0 '
b0 3
b0 >
b0 Q
b11 E
b10 H
0J
04
1"
#185
b11 &
b11 8
1J
14
0"
#190
0(
b1 >
b1 Q
b1 '
b1 3
15
0.
0J
04
1"
#195
1J
14
0"
#200
b10 '
b10 3
b10 >
b10 Q
0J
04
1"
#205
1J
14
0"
#210
0K
1C
b11 D
1<
b11 >
b11 Q
b11 '
b11 3
0J
04
1"
#215
b10 A
b10 ?
b10 N
1J
14
0"
#220
0<
b100 '
b100 3
b0 >
b0 Q
b10 E
b11 H
1K
0C
0J
04
1"
#225
1J
14
0"
#230
b1 >
b1 Q
b101 '
b101 3
0J
04
1"
#235
1J
14
0"
#240
b110 '
b110 3
b10 >
b10 Q
0J
04
1"
#245
1J
14
0"
#250
b10 D
1<
b11 >
b11 Q
b111 '
b111 3
0J
04
1"
#255
1J
14
0"
#260
0+
05
1.
1(
0<
b0 '
b0 3
b0 >
b0 Q
b11 E
b10 H
0J
04
1"
#265
b100 &
b100 8
1J
14
0"
#270
0(
b1 >
b1 Q
b1 '
b1 3
15
0.
0J
04
1"
#275
1J
14
0"
#280
b10 '
b10 3
b10 >
b10 Q
0J
04
1"
#285
1J
14
0"
#290
0K
1C
b11 D
1<
b11 >
b11 Q
b11 '
b11 3
0J
04
1"
#295
b11 ?
b11 N
1J
14
0"
#300
0<
b100 '
b100 3
b0 >
b0 Q
b10 E
b11 H
1K
0C
0J
04
1"
#305
1J
14
0"
#310
b1 >
b1 Q
b101 '
b101 3
0J
04
1"
#315
1J
14
0"
#320
b110 '
b110 3
b10 >
b10 Q
0J
04
1"
#325
1J
14
0"
#330
b10 D
1<
b11 >
b11 Q
b111 '
b111 3
0J
04
1"
#335
1J
14
0"
#340
1+
05
1.
1(
0<
b0 '
b0 3
b0 >
b0 Q
b11 E
b10 H
0J
04
1"
#345
b101 &
b101 8
1J
14
0"
#350
0(
b1 >
b1 Q
b1 '
b1 3
15
0.
0J
04
1"
#355
1J
14
0"
#360
b10 '
b10 3
b10 >
b10 Q
0J
04
1"
#365
1J
14
0"
#370
0K
1C
b11 D
1<
b11 >
b11 Q
b11 '
b11 3
0J
04
1"
#375
b1010 A
b100 ?
b100 N
1J
14
0"
#380
0<
b100 '
b100 3
b0 >
b0 Q
b10 E
b11 H
1K
0C
0J
04
1"
#385
1J
14
0"
#390
b1 >
b1 Q
b101 '
b101 3
0J
04
1"
#395
1J
14
0"
#400
b110 '
b110 3
b10 >
b10 Q
0J
04
1"
#405
1J
14
0"
#410
b10 D
1<
b11 >
b11 Q
b111 '
b111 3
0J
04
1"
#415
1J
14
0"
#420
0+
05
1.
1(
0<
b0 '
b0 3
b0 >
b0 Q
b11 E
b10 H
0J
04
1"
#425
b110 &
b110 8
1J
14
0"
#430
0(
b1 >
b1 Q
b1 '
b1 3
15
0.
0J
04
1"
#435
1J
14
0"
#440
b10 '
b10 3
b10 >
b10 Q
0J
04
1"
#445
1J
14
0"
#450
0K
1C
b11 D
1<
b11 >
b11 Q
b11 '
b11 3
0J
04
1"
#455
b101 ?
b101 N
1J
14
0"
#460
0<
b100 '
b100 3
b0 >
b0 Q
b10 E
b11 H
1K
0C
0J
04
1"
#465
1J
14
0"
#470
b1 >
b1 Q
b101 '
b101 3
0J
04
1"
#475
1J
14
0"
#480
b110 '
b110 3
b10 >
b10 Q
0J
04
1"
#485
1J
14
0"
#490
b10 D
1<
b11 >
b11 Q
b111 '
b111 3
0J
04
1"
#495
1J
14
0"
#500
1+
05
1.
1(
0<
b0 '
b0 3
b0 >
b0 Q
b11 E
b10 H
0J
04
1"
#505
b111 &
b111 8
1J
14
0"
#510
0(
b1 >
b1 Q
b1 '
b1 3
15
0.
0J
04
1"
#515
1J
14
0"
#520
b10 '
b10 3
b10 >
b10 Q
0J
04
1"
#525
1J
14
0"
#530
0K
1C
b11 D
1<
b11 >
b11 Q
b11 '
b11 3
0J
04
1"
#535
b101010 A
b110 ?
b110 N
1J
14
0"
#540
0<
b100 '
b100 3
b0 >
b0 Q
b10 E
b11 H
1K
0C
0J
04
1"
#545
1J
14
0"
#550
b1 >
b1 Q
b101 '
b101 3
0J
04
1"
#555
1J
14
0"
#560
b110 '
b110 3
b10 >
b10 Q
0J
04
1"
#565
1J
14
0"
#570
b10 D
1<
b11 >
b11 Q
b111 '
b111 3
0J
04
1"
#575
1J
14
0"
#580
0+
05
1.
1(
0<
b0 '
b0 3
b0 >
b0 Q
b11 E
b10 H
0J
04
1"
#585
b1000 &
b1000 8
1J
14
0"
#590
0(
b1 >
b1 Q
b1 '
b1 3
15
0.
0J
04
1"
#595
1J
14
0"
#600
b10 '
b10 3
b10 >
b10 Q
0J
04
1"
#605
1J
14
0"
#610
0K
1C
b11 D
1<
b11 >
b11 Q
b11 '
b11 3
0J
04
1"
#615
b111 ?
b111 N
1J
14
0"
#620
0<
b100 '
b100 3
b0 >
b0 Q
b10 E
b11 H
1K
0C
0J
04
1"
#625
1J
14
0"
#630
b1 >
b1 Q
b101 '
b101 3
0J
04
1"
#635
1J
14
0"
#640
b110 '
b110 3
b10 >
b10 Q
0J
04
1"
#645
1J
14
0"
#650
b10 D
1<
b11 >
b11 Q
b111 '
b111 3
0J
04
1"
#655
1J
14
0"
#660
1+
05
1.
1(
0<
b0 '
b0 3
b0 >
b0 Q
b11 E
b10 H
0J
04
1"
#665
b1001 &
b1001 8
1J
14
0"
#670
0(
b1 >
b1 Q
b1 '
b1 3
15
0.
0J
04
1"
#675
1J
14
0"
#680
b10 '
b10 3
b10 >
b10 Q
0J
04
1"
#685
1J
14
0"
#690
0K
1C
b11 D
1<
b11 >
b11 Q
b11 '
b11 3
0J
04
1"
#695
b10101010 A
b1000 ?
b1000 N
1J
14
0"
#700
0<
b100 '
b100 3
b0 >
b0 Q
b10 E
b11 H
1K
0C
0J
04
1"
#705
1J
14
0"
#710
b1 >
b1 Q
b101 '
b101 3
0J
04
1"
#715
1J
14
0"
#720
b110 '
b110 3
b10 >
b10 Q
0J
04
1"
#725
1J
14
0"
#730
b0 ?
b0 N
0:
0@
b100 D
1<
b11 >
b11 Q
b111 '
b111 3
0J
04
1"
#735
1J
14
0"
#740
05
1.
1(
0<
b0 '
b0 3
b0 >
b0 Q
b11 E
b100 H
1:
1@
0J
04
1"
#745
b1010 &
b1010 8
1J
14
0"
#750
0(
b1 >
b1 Q
b1 '
b1 3
15
0.
0J
04
1"
#755
1J
14
0"
#760
b10 '
b10 3
b10 >
b10 Q
0J
04
1"
#765
1J
14
0"
#770
b0 A
b10101010 F
1I
b0 D
1<
b11 >
b11 Q
b11 '
b11 3
0J
04
1"
#775
1J
14
0"
#780
0<
b100 '
b100 3
b0 >
b0 Q
b100 E
b0 H
0I
0J
04
1"
#785
1J
14
0"
#790
b1 >
b1 Q
b101 '
b101 3
0J
04
1"
#795
1J
14
0"
#800
b110 '
b110 3
b10 >
b10 Q
0J
04
1"
#805
1J
14
0"
#810
1<
b11 >
b11 Q
b111 '
b111 3
0J
04
1"
#815
1J
14
0"
#820
b0 &
b0 8
b1111100000 )
1(
0<
0/
0*
b0 '
b0 3
00
b0 >
b0 Q
b0 E
1+
1,
15
0.
0J
04
1"
1$
b11110000 %
#825
1J
14
0"
#830
b1 D
0+
0(
1*
05
1.
b1 >
b1 Q
10
b1 '
b1 3
1/
0J
04
1"
0$
#835
b1 &
b1 8
1J
14
0"
#840
b10 '
b10 3
b10 >
b10 Q
b1 H
15
0.
0J
04
1"
#845
1J
14
0"
#850
b11 D
1<
b11 >
b11 Q
b11 '
b11 3
0J
04
1"
#855
1J
14
0"
#860
0<
b100 '
b100 3
b0 >
b0 Q
b1 E
b11 H
0J
04
1"
#865
1J
14
0"
#870
b1 >
b1 Q
b101 '
b101 3
0J
04
1"
#875
1J
14
0"
#880
b110 '
b110 3
b10 >
b10 Q
0J
04
1"
#885
1J
14
0"
#890
b10 D
1<
b11 >
b11 Q
b111 '
b111 3
0J
04
1"
#895
1J
14
0"
#900
05
1.
1(
0<
b0 '
b0 3
b0 >
b0 Q
b11 E
b10 H
0J
04
1"
#905
b10 &
b10 8
1J
14
0"
#910
0(
b1 >
b1 Q
b1 '
b1 3
15
0.
0J
04
1"
#915
1J
14
0"
#920
b10 '
b10 3
b10 >
b10 Q
0J
04
1"
#925
1J
14
0"
#930
0K
1C
b11 D
1<
b11 >
b11 Q
b11 '
b11 3
0J
04
1"
#935
b1 ?
b1 N
1J
14
0"
#940
0<
b100 '
b100 3
b0 >
b0 Q
b10 E
b11 H
1K
0C
0J
04
1"
#945
1J
14
0"
#950
b1 >
b1 Q
b101 '
b101 3
0J
04
1"
#955
1J
14
0"
#960
b110 '
b110 3
b10 >
b10 Q
0J
04
1"
#965
1J
14
0"
#970
b10 D
1<
b11 >
b11 Q
b111 '
b111 3
0J
04
1"
#975
1J
14
0"
#980
05
1.
1(
0<
b0 '
b0 3
b0 >
b0 Q
b11 E
b10 H
0J
04
1"
#985
b11 &
b11 8
1J
14
0"
#990
0(
b1 >
b1 Q
b1 '
b1 3
15
0.
0J
04
1"
#995
1J
14
0"
#1000
b10 '
b10 3
b10 >
b10 Q
0J
04
1"
#1005
1J
14
0"
#1010
0K
1C
b11 D
1<
b11 >
b11 Q
b11 '
b11 3
0J
04
1"
#1015
b10 ?
b10 N
1J
14
0"
#1020
0<
b100 '
b100 3
b0 >
b0 Q
b10 E
b11 H
1K
0C
0J
04
1"
#1025
1J
14
0"
#1030
b1 >
b1 Q
b101 '
b101 3
0J
04
1"
#1035
1J
14
0"
#1040
b110 '
b110 3
b10 >
b10 Q
0J
04
1"
#1045
1J
14
0"
#1050
b10 D
1<
b11 >
b11 Q
b111 '
b111 3
0J
04
1"
#1055
1J
14
0"
#1060
05
1.
1(
0<
b0 '
b0 3
b0 >
b0 Q
b11 E
b10 H
0J
04
1"
#1065
b100 &
b100 8
1J
14
0"
#1070
0(
b1 >
b1 Q
b1 '
b1 3
15
0.
0J
04
1"
#1075
1J
14
0"
#1080
b10 '
b10 3
b10 >
b10 Q
0J
04
1"
#1085
1J
14
0"
#1090
0K
1C
b11 D
1<
b11 >
b11 Q
b11 '
b11 3
0J
04
1"
#1095
b11 ?
b11 N
1J
14
0"
#1100
0<
b100 '
b100 3
b0 >
b0 Q
b10 E
b11 H
1K
0C
0J
04
1"
#1105
1J
14
0"
#1110
b1 >
b1 Q
b101 '
b101 3
0J
04
1"
#1115
1J
14
0"
#1120
b110 '
b110 3
b10 >
b10 Q
0J
04
1"
#1125
1J
14
0"
#1130
b10 D
1<
b11 >
b11 Q
b111 '
b111 3
0J
04
1"
#1135
1J
14
0"
#1140
05
1.
1(
0<
b0 '
b0 3
b0 >
b0 Q
b11 E
b10 H
0J
04
1"
#1145
b101 &
b101 8
1J
14
0"
#1150
0(
b1 >
b1 Q
b1 '
b1 3
15
0.
0J
04
1"
#1155
1J
14
0"
#1160
b10 '
b10 3
b10 >
b10 Q
0J
04
1"
#1165
1J
14
0"
#1170
0K
1C
b11 D
1<
b11 >
b11 Q
b11 '
b11 3
0J
04
1"
#1175
b100 ?
b100 N
1J
14
0"
#1180
0<
b100 '
b100 3
b0 >
b0 Q
b10 E
b11 H
1K
0C
0J
04
1"
#1185
1J
14
0"
#1190
b1 >
b1 Q
b101 '
b101 3
0J
04
1"
#1195
1J
14
0"
#1200
b110 '
b110 3
b10 >
b10 Q
0J
04
1"
#1205
1J
14
0"
#1210
b10 D
1<
b11 >
b11 Q
b111 '
b111 3
0J
04
1"
#1215
1J
14
0"
#1220
1+
05
1.
1(
0<
b0 '
b0 3
b0 >
b0 Q
b11 E
b10 H
0J
04
1"
#1225
b110 &
b110 8
1J
14
0"
#1230
0(
b1 >
b1 Q
b1 '
b1 3
15
0.
0J
04
1"
#1235
1J
14
0"
#1240
b10 '
b10 3
b10 >
b10 Q
0J
04
1"
#1245
1J
14
0"
#1250
0K
1C
b11 D
1<
b11 >
b11 Q
b11 '
b11 3
0J
04
1"
#1255
b10000 A
b101 ?
b101 N
1J
14
0"
#1260
0<
b100 '
b100 3
b0 >
b0 Q
b10 E
b11 H
1K
0C
0J
04
1"
#1265
1J
14
0"
#1270
b1 >
b1 Q
b101 '
b101 3
0J
04
1"
#1275
1J
14
0"
#1280
b110 '
b110 3
b10 >
b10 Q
0J
04
1"
#1285
1J
14
0"
#1290
b10 D
1<
b11 >
b11 Q
b111 '
b111 3
0J
04
1"
#1295
1J
14
0"
#1300
05
1.
1(
0<
b0 '
b0 3
b0 >
b0 Q
b11 E
b10 H
0J
04
1"
#1305
b111 &
b111 8
1J
14
0"
#1310
0(
b1 >
b1 Q
b1 '
b1 3
15
0.
0J
04
1"
#1315
1J
14
0"
#1320
b10 '
b10 3
b10 >
b10 Q
0J
04
1"
#1325
1J
14
0"
#1330
0K
1C
b11 D
1<
b11 >
b11 Q
b11 '
b11 3
0J
04
1"
#1335
b110000 A
b110 ?
b110 N
1J
14
0"
#1340
0<
b100 '
b100 3
b0 >
b0 Q
b10 E
b11 H
1K
0C
0J
04
1"
#1345
1J
14
0"
#1350
b1 >
b1 Q
b101 '
b101 3
0J
04
1"
#1355
1J
14
0"
#1360
b110 '
b110 3
b10 >
b10 Q
0J
04
1"
#1365
1J
14
0"
#1370
b10 D
1<
b11 >
b11 Q
b111 '
b111 3
0J
04
1"
#1375
1J
14
0"
#1380
05
1.
1(
0<
b0 '
b0 3
b0 >
b0 Q
b11 E
b10 H
0J
04
1"
#1385
b1000 &
b1000 8
1J
14
0"
#1390
0(
b1 >
b1 Q
b1 '
b1 3
15
0.
0J
04
1"
#1395
1J
14
0"
#1400
b10 '
b10 3
b10 >
b10 Q
0J
04
1"
#1405
1J
14
0"
#1410
0K
1C
b11 D
1<
b11 >
b11 Q
b11 '
b11 3
0J
04
1"
#1415
b1110000 A
b111 ?
b111 N
1J
14
0"
#1420
0<
b100 '
b100 3
b0 >
b0 Q
b10 E
b11 H
1K
0C
0J
04
1"
#1425
1J
14
0"
#1430
b1 >
b1 Q
b101 '
b101 3
0J
04
1"
#1435
1J
14
0"
#1440
b110 '
b110 3
b10 >
b10 Q
0J
04
1"
#1445
1J
14
0"
#1450
b10 D
1<
b11 >
b11 Q
b111 '
b111 3
0J
04
1"
#1455
1J
14
0"
#1460
05
1.
1(
0<
b0 '
b0 3
b0 >
b0 Q
b11 E
b10 H
0J
04
1"
#1465
b1001 &
b1001 8
1J
14
0"
#1470
0(
b1 >
b1 Q
b1 '
b1 3
15
0.
0J
04
1"
#1475
1J
14
0"
#1480
b10 '
b10 3
b10 >
b10 Q
0J
04
1"
#1485
1J
14
0"
#1490
0K
1C
b11 D
1<
b11 >
b11 Q
b11 '
b11 3
0J
04
1"
#1495
b11110000 A
b1000 ?
b1000 N
1J
14
0"
#1500
0<
b100 '
b100 3
b0 >
b0 Q
b10 E
b11 H
1K
0C
0J
04
1"
#1505
1J
14
0"
#1510
b1 >
b1 Q
b101 '
b101 3
0J
04
1"
#1515
1J
14
0"
#1520
b110 '
b110 3
b10 >
b10 Q
0J
04
1"
#1525
1J
14
0"
#1530
b0 ?
b0 N
0:
0@
b100 D
1<
b11 >
b11 Q
b111 '
b111 3
0J
04
1"
#1535
1J
14
0"
#1540
05
1.
1(
0<
b0 '
b0 3
b0 >
b0 Q
b11 E
b100 H
1:
1@
0J
04
1"
#1545
b1010 &
b1010 8
1J
14
0"
#1550
0(
b1 >
b1 Q
b1 '
b1 3
15
0.
0J
04
1"
#1555
1J
14
0"
#1560
b10 '
b10 3
b10 >
b10 Q
0J
04
1"
#1565
1J
14
0"
#1570
b0 A
b11110000 F
1I
b0 D
1<
b11 >
b11 Q
b11 '
b11 3
0J
04
1"
#1575
1J
14
0"
#1580
0<
b100 '
b100 3
b0 >
b0 Q
b100 E
b0 H
0I
0J
04
1"
#1585
1J
14
0"
